olliepy/InteractiveDashboard.py
olliepy/RegressionErrorAnalysisReport.py
olliepy/Report.py
olliepy/__init__.py
reports-templates/interactive-dashboard/app.py
reports-templates/interactive-dashboard/css/app.8951237e.css
reports-templates/interactive-dashboard/favicon.ico
reports-templates/interactive-dashboard/fonts/MaterialIcons-Regular.0509ab09.woff2
reports-templates/interactive-dashboard/fonts/MaterialIcons-Regular.29b882f0.woff
reports-templates/interactive-dashboard/fonts/MaterialIcons-Regular.96c47680.eot
reports-templates/interactive-dashboard/fonts/MaterialIcons-Regular.da4ea5cd.ttf
reports-templates/interactive-dashboard/img/logo.1e360cb2.png
reports-templates/interactive-dashboard/index.html
reports-templates/interactive-dashboard/js/app.0e0ecaf7.js
reports-templates/interactive-dashboard/js/app.0e0ecaf7.js.map
reports-templates/interactive-dashboard/start_dashboard.bat
reports-templates/interactive-dashboard/start_dashboard.sh
reports-templates/regression-error-analysis-report/app.py
reports-templates/regression-error-analysis-report/css/app.63e3895e.css
reports-templates/regression-error-analysis-report/favicon.ico
reports-templates/regression-error-analysis-report/fonts/MaterialIcons-Regular.0509ab09.woff2
reports-templates/regression-error-analysis-report/fonts/MaterialIcons-Regular.29b882f0.woff
reports-templates/regression-error-analysis-report/fonts/MaterialIcons-Regular.96c47680.eot
reports-templates/regression-error-analysis-report/fonts/MaterialIcons-Regular.da4ea5cd.ttf
reports-templates/regression-error-analysis-report/img/logo.1e360cb2.png
reports-templates/regression-error-analysis-report/index.html
reports-templates/regression-error-analysis-report/js/app.2445095e.js
reports-templates/regression-error-analysis-report/js/app.2445095e.js.map
reports-templates/regression-error-analysis-report/start_dashboard.bat
reports-templates/regression-error-analysis-report/start_dashboard.sh
olliepy-0.2.9.dist-info/LICENSE
olliepy-0.2.9.dist-info/WHEEL
olliepy-0.2.9.dist-info/METADATA
olliepy-0.2.9.dist-info/RECORD
